{
    "head": {
        "vars": [
            "movie",
            "movieLabel",
            "trophy",
            "trophyLabel",
            "awardScope"
        ]
    },
    "results": {
        "bindings": [
            {
                "movie": {
                    "type": "uri",
                    "value": "http://www.wikidata.org/entity/Q6074"
                },
                "trophy": {
                    "type": "uri",
                    "value": "http://www.wikidata.org/entity/Q4376972"
                },
                "awardScope": {
                    "type": "literal",
                    "value": "film"
                },
                "movieLabel": {
                    "xml:lang": "fr",
                    "type": "literal",
                    "value": "Star Wars, \u00e9pisode VII : Le R\u00e9veil de la Force"
                },
                "trophyLabel": {
                    "xml:lang": "en",
                    "type": "literal",
                    "value": "Grammy Award for Best Score Soundtrack for Visual Media"
                }
            },
            {
                "movie": {
                    "type": "uri",
                    "value": "http://www.wikidata.org/entity/Q134773"
                },
                "trophy": {
                    "type": "uri",
                    "value": "http://www.wikidata.org/entity/Q654620"
                },
                "awardScope": {
                    "type": "literal",
                    "value": "acteur"
                },
                "movieLabel": {
                    "type": "literal",
                    "value": "Q134773"
                },
                "trophyLabel": {
                    "xml:lang": "fr",
                    "type": "literal",
                    "value": "Screen Actors Guild Award du meilleur acteur dans un premier r\u00f4le"
                }
            },
            {
                "movie": {
                    "type": "uri",
                    "value": "http://www.wikidata.org/entity/Q134773"
                },
                "trophy": {
                    "type": "uri",
                    "value": "http://www.wikidata.org/entity/Q393686"
                },
                "awardScope": {
                    "type": "literal",
                    "value": "film"
                },
                "movieLabel": {
                    "type": "literal",
                    "value": "Q134773"
                },
                "trophyLabel": {
                    "xml:lang": "fr",
                    "type": "literal",
                    "value": "Oscar des meilleurs effets visuels"
                }
            }
        ]
    }
}